defog_data.py
defog_data/__init__.py
defog_data/metadata.py
defog_data/supplementary.py
defog_data/academic/academic.json
defog_data/academic/academic.sql
defog_data/advising/advising.json
defog_data/advising/advising.sql
defog_data/atis/atis.json
defog_data/atis/atis.sql
defog_data/geography/geography.json
defog_data/geography/geography.sql
defog_data/restaurants/restaurants.json
defog_data/restaurants/restaurants.sql
defog_data/scholar/scholar.json
defog_data/scholar/scholar.sql
defog_data/yelp/yelp.json
defog_data/yelp/yelp.sql
defog_data-0.1.1.dist-info/LICENSE
defog_data-0.1.1.dist-info/METADATA
defog_data-0.1.1.dist-info/WHEEL
defog_data-0.1.1.dist-info/top_level.txt
defog_data-0.1.1.dist-info/RECORD
